LICENSE
README.md
setup.py
aioinflux3/__init__.py
aioinflux3/client.py
aioinflux3/exceptions.py
aioinflux3/line_protocal.py
aioinflux3.egg-info/PKG-INFO
aioinflux3.egg-info/SOURCES.txt
aioinflux3.egg-info/dependency_links.txt
aioinflux3.egg-info/requires.txt
aioinflux3.egg-info/top_level.txt