Metadata-Version: 2.1
Name: aioinflux3
Version: 0.0.4
Summary: influxdb python client working with asyncio
Home-page: https://github.com/ipconfiger/aio-influx
Author: Alexander.Li
Author-email: superpowerlee@gmail.com
License: UNKNOWN
Platform: UNKNOWN
License-File: LICENSE
